rest_requests/__init__.py
rest_requests/rest_request.py
rest_requests/rest_request_executor.py
steering/__init__.py
steering/answer_parser.py
steering/question.py
Weather_rest_library-1.0.2.dist-info/License.txt
Weather_rest_library-1.0.2.dist-info/METADATA
Weather_rest_library-1.0.2.dist-info/WHEEL
Weather_rest_library-1.0.2.dist-info/top_level.txt
Weather_rest_library-1.0.2.dist-info/RECORD
