Metadata-Version: 2.1
Name: Weather-rest-library
Version: 1.0.2
Summary: Useful towel-related stuff.
Home-page: https://git.e-science.pl/murbanczyk_252808/murbanczyk252808_dpp_python_pip
Author: Mateusz Urbańczyk
Author-email: name@addr.ess
License: UNKNOWN
Platform: UNKNOWN
License-File: License.txt
Requires-Dist: requests
